[
  {
    "credit": 4,
    "id": "COEN0031112043",
    "name": "体育赛事英语",
    "offerings": [
      {
        "id": "04",
        "teacher": "韦玮",
        "times": [
          0,
          96,
          0,
          0,
          0,
          0,
          0
        ],
        "weeks": 262143
      }
    ],
    "prerequisites": [
      "COEN0031111109"
    ],
    "required": "Elective",
    "semester": "Spring"
  },
  {
    "credit": 6,
    "id": "SHKX0031111016",
    "name": "思想道德与法治",
    "offerings": [
      {
        "id": "24",
        "teacher": "祝毅讲师",
        "times": [
          0,
          7168,
          0,
          0,
          0,
          0,
          0
        ],
        "weeks": 262143
      },
      {
        "id": "06",
        "teacher": "白雪源讲师",
        "times": [
          7168,
          0,
          0,
          0,
          0,
          0,
          0
        ],
        "weeks": 262143
      }
    ],
    "prerequisites": [],
    "required": "Compulsory",
    "semester": "Autumn"
  },
  {
    "credit": 8,
    "id": "COMS0031161000",
    "name": "大学物理B（二）",
    "offerings": [
      {
        "id": "01",
        "teacher": "李波教授",
        "times": [
          0,
          96,
          0,
          12,
          0,
          0,
          0
        ],
        "weeks": 262143
      },
      {
        "id": "02",
        "teacher": "李亚巍副教授",
        "times": [
          0,
          12,
          0,
          12,
          0,
          0,
          0
        ],
        "weeks": 262143
      },
      {
        "id": "03",
        "teacher": "商丽燕副教授",
        "times": [
          0,
          12,
          0,
          12,
          0,
          0,
          0
        ],
        "weeks": 262143
      }
    ],
    "prerequisites": [
      "COMS0031161001"
    ],
    "required": "Compulsory",
    "semester": "Spring"
  },
  {
    "credit": 6,
    "id": "COMS0031132126",
    "name": "现代CAD技术（B）",
    "offerings": [
      {
        "id": "01",
        "teacher": "宋海川副教授",
        "times": [
          15,
          0,
          0,
          0,
          0,
          0,
          0
        ],
        "weeks": 174762
      }
    ],
    "prerequisites": [
      "COMS0031132125"
    ],
    "required": "Elective",
    "semester": "Spring"
  },
  {
    "credit": 5,
    "id": "COMS0031132120",
    "name": "最优化方法",
    "offerings": [
      {
        "id": "01",
        "teacher": "王祥丰教授",
        "times": [
          0,
          0,
          0,
          0,
          15,
          0,
          0
        ],
        "weeks": 262143
      }
    ],
    "prerequisites": [
      "COMS0031131032"
    ],
    "required": "Elective",
    "semester": "Spring",
    "priority": 3
  }
]
